aliyunsdkcc5g/__init__.py
aliyunsdkcc5g/request/__init__.py
aliyunsdkcc5g/request/v20220314/AddDNSAuthorizationRuleRequest.py
aliyunsdkcc5g/request/v20220314/AddGroupDnsAuthorizationRuleRequest.py
aliyunsdkcc5g/request/v20220314/AddWirelessCloudConnectorToGroupRequest.py
aliyunsdkcc5g/request/v20220314/AttachVpcToNetLinkRequest.py
aliyunsdkcc5g/request/v20220314/CreateAuthorizationRuleRequest.py
aliyunsdkcc5g/request/v20220314/CreateBatchOperateCardsTaskRequest.py
aliyunsdkcc5g/request/v20220314/CreateGroupAuthorizationRuleRequest.py
aliyunsdkcc5g/request/v20220314/CreateIoTCloudConnectorBackhaulRouteRequest.py
aliyunsdkcc5g/request/v20220314/CreateWirelessCloudConnectorGroupRequest.py
aliyunsdkcc5g/request/v20220314/CreateWirelessCloudConnectorRequest.py
aliyunsdkcc5g/request/v20220314/DeleteAuthorizationRuleRequest.py
aliyunsdkcc5g/request/v20220314/DeleteBatchOperateCardsTaskRequest.py
aliyunsdkcc5g/request/v20220314/DeleteGroupAuthorizationRuleRequest.py
aliyunsdkcc5g/request/v20220314/DeleteIoTCloudConnectorBackhaulRouteRequest.py
aliyunsdkcc5g/request/v20220314/DeleteWirelessCloudConnectorGroupRequest.py
aliyunsdkcc5g/request/v20220314/DeleteWirelessCloudConnectorRequest.py
aliyunsdkcc5g/request/v20220314/DetachVpcFromNetLinkRequest.py
aliyunsdkcc5g/request/v20220314/FailCardsRequest.py
aliyunsdkcc5g/request/v20220314/GetCardLockReasonRequest.py
aliyunsdkcc5g/request/v20220314/GetCardRequest.py
aliyunsdkcc5g/request/v20220314/GetCreateCustomerInformationRequest.py
aliyunsdkcc5g/request/v20220314/GetDiagnoseResultForSingleCardRequest.py
aliyunsdkcc5g/request/v20220314/GetWirelessCloudConnectorRequest.py
aliyunsdkcc5g/request/v20220314/GrantNetLinkRequest.py
aliyunsdkcc5g/request/v20220314/ListAPNsRequest.py
aliyunsdkcc5g/request/v20220314/ListAuthorizationRulesRequest.py
aliyunsdkcc5g/request/v20220314/ListBatchOperateCardsTasksRequest.py
aliyunsdkcc5g/request/v20220314/ListCardDayUsagesRequest.py
aliyunsdkcc5g/request/v20220314/ListCardUsagesRequest.py
aliyun_python_sdk_cc5g-1.0.7.dist-info/LICENSE
aliyun_python_sdk_cc5g-1.0.7.dist-info/METADATA
aliyun_python_sdk_cc5g-1.0.7.dist-info/WHEEL
aliyun_python_sdk_cc5g-1.0.7.dist-info/top_level.txt
aliyun_python_sdk_cc5g-1.0.7.dist-info/RECORD
